httpx/__init__.py
httpx/__version__.py
httpx/_api.py
httpx/_auth.py
httpx/_client.py
httpx/_compat.py
httpx/_config.py
httpx/_content.py
httpx/_decoders.py
httpx/_exceptions.py
httpx/_main.py
httpx/_models.py
httpx/_multipart.py
httpx/_status_codes.py
httpx/_types.py
httpx/_urlparse.py
httpx/_urls.py
httpx/_utils.py
httpx/_transports/__init__.py
httpx/_transports/asgi.py
httpx/_transports/base.py
httpx/_transports/default.py
httpx/_transports/mock.py
httpx/_transports/wsgi.py
httpx_with_httpcore_with_random_feature_branch-0.25.1.dist-info/METADATA
httpx_with_httpcore_with_random_feature_branch-0.25.1.dist-info/WHEEL
httpx_with_httpcore_with_random_feature_branch-0.25.1.dist-info/entry_points.txt
httpx_with_httpcore_with_random_feature_branch-0.25.1.dist-info/licenses/LICENSE.md
httpx_with_httpcore_with_random_feature_branch-0.25.1.dist-info/RECORD
